a1_coverage.pth
coverage/__init__.py
coverage/__main__.py
coverage/annotate.py
coverage/bytecode.py
coverage/cmdline.py
coverage/collector.py
coverage/config.py
coverage/context.py
coverage/control.py
coverage/core.py
coverage/data.py
coverage/debug.py
coverage/disposition.py
coverage/env.py
coverage/exceptions.py
coverage/execfile.py
coverage/files.py
coverage/html.py
coverage/inorout.py
coverage/jsonreport.py
coverage/lcovreport.py
coverage/misc.py
coverage/multiproc.py
coverage/numbits.py
coverage/parser.py
coverage/patch.py
coverage/phystokens.py
coverage/plugin.py
coverage/plugin_support.py
coverage/pth_file.py
coverage/py.typed
coverage/python.py
coverage/pytracer.py
coverage/regions.py
coverage/report.py
coverage/report_core.py
coverage/results.py
coverage/sqldata.py
coverage/sqlitedb.py
coverage/sysmon.py
coverage/templite.py
coverage/tomlconfig.py
coverage/tracer.pyi
coverage/types.py
coverage/version.py
coverage/xmlreport.py
coverage/htmlfiles/coverage_html.js
coverage/htmlfiles/favicon_32.png
coverage/htmlfiles/index.html
coverage/htmlfiles/keybd_closed.png
coverage/htmlfiles/pyfile.html
coverage/htmlfiles/style.css
coverage/htmlfiles/style.scss
coverage-7.13.1.dist-info/licenses/LICENSE.txt
coverage-7.13.1.dist-info/METADATA
coverage-7.13.1.dist-info/WHEEL
coverage-7.13.1.dist-info/entry_points.txt
coverage-7.13.1.dist-info/top_level.txt
coverage-7.13.1.dist-info/RECORD
