Metadata-Version: 2.4
Name: coverage
Version: 7.13.1
Summary: Code coverage measurement for Python
Home-page: https://github.com/coveragepy/coveragepy
Author: Ned Batchelder and 254 others
Author-email: ned@nedbatchelder.com
License: Apache-2.0
Project-URL: Documentation, https://coverage.readthedocs.io/en/7.13.1
Project-URL: Funding, https://tidelift.com/subscription/pkg/pypi-coverage?utm_source=pypi-coverage&utm_medium=referral&utm_campaign=pypi
Project-URL: Issues, https://github.com/coveragepy/coveragepy/issues
Project-URL: Mastodon, https://hachyderm.io/@coveragepy
Project-URL: Mastodon (nedbat), https://hachyderm.io/@nedbat
Keywords: code coverage testing
Classifier: Development Status :: 5 - Production/Stable
Classifier: Environment :: Console
Classifier: Intended Audience :: Developers
Classifier: Operating System :: OS Independent
Classifier: Programming Language :: Python
Classifier: Programming Language :: Python :: 3
Classifier: Programming Language :: Python :: 3.10
Classifier: Programming Language :: Python :: 3.11
Classifier: Programming Language :: Python :: 3.12
Classifier: Programming Language :: Python :: 3.13
Classifier: Programming Language :: Python :: 3.14
Classifier: Programming Language :: Python :: 3.15
Classifier: Programming Language :: Python :: Free Threading :: 3 - Stable
Classifier: Programming Language :: Python :: Implementation :: CPython
Classifier: Programming Language :: Python :: Implementation :: PyPy
Classifier: Topic :: Software Development :: Quality Assurance
Classifier: Topic :: Software Development :: Testing
Requires-Python: >=3.10
License-File: LICENSE.txt
Provides-Extra: toml
Requires-Dist: tomli; python_full_version <= "3.11.0a6" and extra == "toml"
Dynamic: author
Dynamic: author-email
Dynamic: classifier
Dynamic: description
Dynamic: description-content-type
Dynamic: home-page
Dynamic: keywords
Dynamic: license
Dynamic: license-file
Dynamic: project-url
Dynamic: provides-extra
Dynamic: requires-python
Dynamic: summary
